poetry_k6sy_demo/__init__.py
poetry_k6sy_demo/app.py
poetry_k6sy_demo-0.1.0.dist-info/WHEEL
poetry_k6sy_demo-0.1.0.dist-info/METADATA
poetry_k6sy_demo-0.1.0.dist-info/RECORD
