Metadata-Version: 2.1
Name: poetry-k6sy-demo
Version: 0.1.0
Summary: 
Author: Kalidou SY
Author-email: kalidou.harouna.sy@gmail.com
Requires-Python: >=3.9,<4.0
Classifier: Programming Language :: Python :: 3
Classifier: Programming Language :: Python :: 3.10
Classifier: Programming Language :: Python :: 3.9
Requires-Dist: Flask (>=2.1.3,<3.0.0)
